flask_simpleldap/__init__.py
Flask_SimpleLDAP-2.0.0.dist-info/LICENSE
Flask_SimpleLDAP-2.0.0.dist-info/METADATA
Flask_SimpleLDAP-2.0.0.dist-info/WHEEL
Flask_SimpleLDAP-2.0.0.dist-info/top_level.txt
Flask_SimpleLDAP-2.0.0.dist-info/RECORD
