Metadata-Version: 2.1
Name: Flask-SimpleLDAP
Version: 2.0.0
Summary: LDAP authentication extension for Flask
Home-page: https://github.com/alexferl/flask-simpleldap
Author: Alexandre Ferland
Author-email: me@alexferl.com
License: MIT
Classifier: Environment :: Web Environment
Classifier: Intended Audience :: Developers
Classifier: License :: OSI Approved :: MIT License
Classifier: Operating System :: OS Independent
Classifier: Programming Language :: Python :: 3.8
Classifier: Programming Language :: Python :: 3.9
Classifier: Programming Language :: Python :: 3.10
Classifier: Programming Language :: Python :: 3.11
Classifier: Programming Language :: Python :: 3.12
Classifier: Topic :: Software Development :: Libraries :: Python Modules
Requires-Python: >=3.8
License-File: LICENSE
Requires-Dist: Flask >=2.2.5
Requires-Dist: python-ldap >=3.0.0
